[
  {
    "_standIn": true,
    "_source": "registration_form",
    "form_id": "rf_7383832",
    "child_name": "Sara Jr",
    "parent_email": "sara.cohen240@example.com",
    "parent_phone": "(927) 555-4201",
    "campus": "Georgetown",
    "weeks": 2,
    "utm_source": "summer_site",
    "utm_medium": "referral",
    "utm_campaign": "summer_camp_2026",
    "created_at": "2026-06-15T00:00:00.000Z",
    "match_key": "517e86568bac3eba758f022554a27956e6cbec3f6e48d02c157ff1e488ab6717"
  },
  {
    "_standIn": true,
    "_source": "registration_form",
    "form_id": "rf_6397213",
    "child_name": "Sofia Jr",
    "parent_email": "sofia.brooks86@example.com",
    "parent_phone": "(249) 555-3196",
    "campus": "Georgetown",
    "weeks": 2,
    "utm_source": "summer_site",
    "utm_medium": "referral",
    "utm_campaign": "summer_camp_2026",
    "created_at": "2026-06-07T00:00:00.000Z",
    "match_key": "e87b6c9dde5b8cd4cca54af928d8abd0a0977ed1560c352cca86d5bd812c9606"
  },
  {
    "_standIn": true,
    "_source": "registration_form",
    "form_id": "rf_0713057",
    "child_name": "Arjun Jr",
    "parent_email": "arjun.chen230@example.com",
    "parent_phone": "(937) 555-4707",
    "campus": "Houston",
    "weeks": 2,
    "utm_source": "summer_site",
    "utm_medium": "referral",
    "utm_campaign": "summer_camp_2026",
    "created_at": "2026-06-03T00:00:00.000Z",
    "match_key": "99acaf9b33dc74cde109f4f709d11eb73170d811a7541564f971e2d969fde2be"
  },
  {
    "_standIn": true,
    "_source": "registration_form",
    "form_id": "rf_6381894",
    "child_name": "Aisha Jr",
    "parent_email": "aisha.kim1128@example.com",
    "parent_phone": "(637) 555-5944",
    "campus": "Dallas",
    "weeks": 2,
    "utm_source": "summer_site",
    "utm_medium": "referral",
    "utm_campaign": "summer_camp_2026",
    "created_at": "2026-06-10T00:00:00.000Z",
    "match_key": "12c3cb9420fbdd396951623a4b7749d0bfb962286a75a576a991f2ff4aca83e6"
  },
  {
    "_standIn": true,
    "_source": "registration_form",
    "form_id": "rf_4810124",
    "child_name": "Jonah Jr",
    "parent_email": "jonah.chen78@example.com",
    "parent_phone": "(800) 555-5220",
    "campus": "Austin",
    "weeks": 2,
    "utm_source": "summer_site",
    "utm_medium": "referral",
    "utm_campaign": "summer_camp_2026",
    "created_at": "2026-08-01T00:00:00.000Z",
    "match_key": "3880c1781294e26b953dd245d105ab156ee28eeaa3fa347d3698099002499d9b"
  },
  {
    "_standIn": true,
    "_source": "registration_form",
    "form_id": "rf_2846223",
    "child_name": "Nina Jr",
    "parent_email": "nina.adams179@example.com",
    "parent_phone": "(739) 555-1302",
    "campus": "Georgetown",
    "weeks": 2,
    "utm_source": "summer_site",
    "utm_medium": "referral",
    "utm_campaign": "summer_camp_2026",
    "created_at": "2026-07-10T00:00:00.000Z",
    "match_key": "ad02c3511afa31e044c6c9b209275e27d474a9693753eda64578a5fe2b7a85fd"
  },
  {
    "_standIn": true,
    "_source": "registration_form",
    "form_id": "rf_5759458",
    "child_name": "Aisha Jr",
    "parent_email": "aisha.johnson1171@example.com",
    "parent_phone": "(967) 555-5945",
    "campus": "Houston",
    "weeks": 1,
    "utm_source": "summer_site",
    "utm_medium": "referral",
    "utm_campaign": "summer_camp_2026",
    "created_at": "2026-08-29T00:00:00.000Z",
    "match_key": "ab991c0fbe8cfaa82a13b2c497000bb6efa421ee4902366edac9e03ff25efd7a"
  },
  {
    "_standIn": true,
    "_source": "registration_form",
    "form_id": "rf_8278811",
    "child_name": "Aisha Jr",
    "parent_email": "aisha.singh1024@example.com",
    "parent_phone": "(273) 555-6774",
    "campus": "Dallas",
    "weeks": 2,
    "utm_source": "summer_site",
    "utm_medium": "referral",
    "utm_campaign": "summer_camp_2026",
    "created_at": "2026-06-15T00:00:00.000Z",
    "match_key": "cb9b4c0b12ddcc15bb0c10d0e9f92b3b859fe0f153266d296c25506d619847ed"
  },
  {
    "_standIn": true,
    "_source": "registration_form",
    "form_id": "rf_4902828",
    "child_name": "Priya Jr",
    "parent_email": "priya.khan898@example.com",
    "parent_phone": "(389) 555-7500",
    "campus": "Dallas",
    "weeks": 2,
    "utm_source": "summer_site",
    "utm_medium": "referral",
    "utm_campaign": "summer_camp_2026",
    "created_at": "2026-08-04T00:00:00.000Z",
    "match_key": "e5127a59aecff26e16c3a9b7078a30f8933260f1b7307fd55574ffd21c455ea0"
  },
  {
    "_standIn": true,
    "_source": "registration_form",
    "form_id": "rf_6100122",
    "child_name": "Diego Jr",
    "parent_email": "diego.singh1154@example.com",
    "parent_phone": "(352) 555-6887",
    "campus": "Dallas",
    "weeks": 2,
    "utm_source": "summer_site",
    "utm_medium": "referral",
    "utm_campaign": "summer_camp_2026",
    "created_at": "2026-06-24T00:00:00.000Z",
    "match_key": "9a8abbe7fc0e4c8ae1b25f87dcc88a234d08261eef5dd259a57229851492d216"
  },
  {
    "_standIn": true,
    "_source": "registration_form",
    "form_id": "rf_9851602",
    "child_name": "Kai Jr",
    "parent_email": "kai.chen809@example.com",
    "parent_phone": "(340) 555-5313",
    "campus": "Georgetown",
    "weeks": 2,
    "utm_source": "summer_site",
    "utm_medium": "referral",
    "utm_campaign": "summer_camp_2026",
    "created_at": "2026-07-14T00:00:00.000Z",
    "match_key": "5ccdce64ef824d76e67b211319e49f8ec81fede9d457b984ead1b4eff17f54c2"
  },
  {
    "_standIn": true,
    "_source": "registration_form",
    "form_id": "rf_2358291",
    "child_name": "Mateo Jr",
    "parent_email": "mateo.kim157@example.com",
    "parent_phone": "(988) 555-6225",
    "campus": "Austin",
    "weeks": 2,
    "utm_source": "summer_site",
    "utm_medium": "referral",
    "utm_campaign": "summer_camp_2026",
    "created_at": "2026-06-12T00:00:00.000Z",
    "match_key": "6e41373487270962bfc3c20a2d84a7b3f9c95cd503c29137cc51de1e6f3bd6ee"
  },
  {
    "_standIn": true,
    "_source": "registration_form",
    "form_id": "rf_0886342",
    "child_name": "Sara Jr",
    "parent_email": "sara.chen475@example.com",
    "parent_phone": "(471) 555-8368",
    "campus": "Houston",
    "weeks": 1,
    "utm_source": "summer_site",
    "utm_medium": "referral",
    "utm_campaign": "summer_camp_2026",
    "created_at": "2026-06-29T00:00:00.000Z",
    "match_key": "1ca2db2572afc4319f35eb4ec6f4e004fe42bc758379cb51b83aac3d8c7868b5"
  },
  {
    "_standIn": true,
    "_source": "registration_form",
    "form_id": "rf_9460884",
    "child_name": "Aisha Jr",
    "parent_email": "aisha.cohen360@example.com",
    "parent_phone": "(358) 555-9706",
    "campus": "Houston",
    "weeks": 1,
    "utm_source": "summer_site",
    "utm_medium": "referral",
    "utm_campaign": "summer_camp_2026",
    "created_at": "2026-06-21T00:00:00.000Z",
    "match_key": "368cb30499d7be244200d70389f2653158acc2cdddc2d37fb46c37e20e88cfb5"
  },
  {
    "_standIn": true,
    "_source": "registration_form",
    "form_id": "rf_5508488",
    "child_name": "Caleb Jr",
    "parent_email": "caleb.kim766@example.com",
    "parent_phone": "(276) 555-1899",
    "campus": "Georgetown",
    "weeks": 2,
    "utm_source": "summer_site",
    "utm_medium": "referral",
    "utm_campaign": "summer_camp_2026",
    "created_at": "2026-08-05T00:00:00.000Z",
    "match_key": "7e0ca9f2218d7ba844e8797bc9f5ac500e26d91d9ec884c487453700d250e085"
  },
  {
    "_standIn": true,
    "_source": "registration_form",
    "form_id": "rf_1804892",
    "child_name": "Diego Jr",
    "parent_email": "diego.johnson314@example.com",
    "parent_phone": "(770) 555-7942",
    "campus": "Dallas",
    "weeks": 2,
    "utm_source": "summer_site",
    "utm_medium": "referral",
    "utm_campaign": "summer_camp_2026",
    "created_at": "2026-06-14T00:00:00.000Z",
    "match_key": "8ecbb7e44ef0dee09a6317ee3ba535d53512839601c0f663457152f06d4fe22f"
  },
  {
    "_standIn": true,
    "_source": "registration_form",
    "form_id": "rf_3258574",
    "child_name": "Liam Jr",
    "parent_email": "liam.patel927@example.com",
    "parent_phone": "(242) 555-8587",
    "campus": "Houston",
    "weeks": 1,
    "utm_source": "summer_site",
    "utm_medium": "referral",
    "utm_campaign": "summer_camp_2026",
    "created_at": "2026-06-19T00:00:00.000Z",
    "match_key": "e0ae61eb11b0adc52b2d526dc519e44ca66bae17b404cfdba45d5fd4883d40a9"
  },
  {
    "_standIn": true,
    "_source": "registration_form",
    "form_id": "rf_7249070",
    "child_name": "Jonah Jr",
    "parent_email": "jonah.okafor569@example.com",
    "parent_phone": "(903) 555-6860",
    "campus": "Dallas",
    "weeks": 2,
    "utm_source": "summer_site",
    "utm_medium": "referral",
    "utm_campaign": "summer_camp_2026",
    "created_at": "2026-07-24T00:00:00.000Z",
    "match_key": "fa51e3d1cde8be960369c248b43e375744005f845e27c0a8829efa4d954dd996"
  },
  {
    "_standIn": true,
    "_source": "registration_form",
    "form_id": "rf_8078637",
    "child_name": "Zoe Jr",
    "parent_email": "zoe.garcia162@example.com",
    "parent_phone": "(437) 555-3116",
    "campus": "Austin",
    "weeks": 2,
    "utm_source": "summer_site",
    "utm_medium": "referral",
    "utm_campaign": "summer_camp_2026",
    "created_at": "2026-08-07T00:00:00.000Z",
    "match_key": "5fbdc67552eea34e5188e017d684c0e4983007a514c5804165ec8f6c77a7d702"
  },
  {
    "_standIn": true,
    "_source": "registration_form",
    "form_id": "rf_7829823",
    "child_name": "Maya Jr",
    "parent_email": "maya.kim354@example.com",
    "parent_phone": "(842) 555-7464",
    "campus": "Georgetown",
    "weeks": 2,
    "utm_source": "summer_site",
    "utm_medium": "referral",
    "utm_campaign": "summer_camp_2026",
    "created_at": "2026-07-26T00:00:00.000Z",
    "match_key": "e046d00258a8b6343cbbf52b7fc1439bfb886076d98541c8000d644de8d5aa20"
  },
  {
    "_standIn": true,
    "_source": "registration_form",
    "form_id": "rf_2029225",
    "child_name": "Chloe Jr",
    "parent_email": "chloe.cohen460@example.com",
    "parent_phone": "(881) 555-9445",
    "campus": "Dallas",
    "weeks": 2,
    "utm_source": "summer_site",
    "utm_medium": "referral",
    "utm_campaign": "summer_camp_2026",
    "created_at": "2026-06-08T00:00:00.000Z",
    "match_key": "470e9ec4e532bfddb60520a0d8c0302a6f86ae99115263785841bae7c2d8c542"
  },
  {
    "_standIn": true,
    "_source": "registration_form",
    "form_id": "rf_9509012",
    "child_name": "Lucas Jr",
    "parent_email": "lucas.garcia558@example.com",
    "parent_phone": "(309) 555-0882",
    "campus": "Georgetown",
    "weeks": 2,
    "utm_source": "summer_site",
    "utm_medium": "referral",
    "utm_campaign": "summer_camp_2026",
    "created_at": "2026-06-01T00:00:00.000Z",
    "match_key": "df7fe9a63d8e3debed6635ab89a391f836a92ee30e3a25247f92ffd7ff51b52e"
  },
  {
    "_standIn": true,
    "_source": "registration_form",
    "form_id": "rf_9912070",
    "child_name": "Mia Jr",
    "parent_email": "mia.cohen168@example.com",
    "parent_phone": "(297) 555-5406",
    "campus": "Houston",
    "weeks": 1,
    "utm_source": "summer_site",
    "utm_medium": "referral",
    "utm_campaign": "summer_camp_2026",
    "created_at": "2026-06-02T00:00:00.000Z",
    "match_key": "5131bfe3e1ecb3ec5cabd2ebfee429800bfa8b9dabe73a43d5c032dbaf418b06"
  },
  {
    "_standIn": true,
    "_source": "registration_form",
    "form_id": "rf_0092357",
    "child_name": "Diego Jr",
    "parent_email": "diego.cohen837@example.com",
    "parent_phone": "(758) 555-6710",
    "campus": "Houston",
    "weeks": 1,
    "utm_source": "summer_site",
    "utm_medium": "referral",
    "utm_campaign": "summer_camp_2026",
    "created_at": "2026-07-14T00:00:00.000Z",
    "match_key": "cbeda70ffd57c65b9d275a37bb6198c283841e9e43c0dcccba491dc0420dc5cc"
  },
  {
    "_standIn": true,
    "_source": "registration_form",
    "form_id": "rf_8850194",
    "child_name": "Theo Jr",
    "parent_email": "theo.schwartz419@example.com",
    "parent_phone": "(595) 555-1110",
    "campus": "Houston",
    "weeks": 1,
    "utm_source": "summer_site",
    "utm_medium": "referral",
    "utm_campaign": "summer_camp_2026",
    "created_at": "2026-07-03T00:00:00.000Z",
    "match_key": "e2211b2bca59561b3f3883794c2e582dd28f4455054a4c9a0793e5f78e01aeae"
  },
  {
    "_standIn": true,
    "_source": "registration_form",
    "form_id": "rf_4584651",
    "child_name": "Hana Jr",
    "parent_email": "hana.kim901@example.com",
    "parent_phone": "(946) 555-4830",
    "campus": "Houston",
    "weeks": 1,
    "utm_source": "summer_site",
    "utm_medium": "referral",
    "utm_campaign": "summer_camp_2026",
    "created_at": "2026-06-09T00:00:00.000Z",
    "match_key": "e58c30937b369f9262bcd6016f4b36b4314669ee4ab73743bac500d06d108594"
  },
  {
    "_standIn": true,
    "_source": "registration_form",
    "form_id": "rf_9602096",
    "child_name": "Marcus Jr",
    "parent_email": "marcus.hernandez973@example.com",
    "parent_phone": "(655) 555-8391",
    "campus": "Austin",
    "weeks": 2,
    "utm_source": "summer_site",
    "utm_medium": "referral",
    "utm_campaign": "summer_camp_2026",
    "created_at": "2026-07-11T00:00:00.000Z",
    "match_key": "c157ad46c2f8f7da0c344560f1a455054127c10f51ee7de7cbd74850b47f6015"
  },
  {
    "_standIn": true,
    "_source": "registration_form",
    "form_id": "rf_0284702",
    "child_name": "Omar Jr",
    "parent_email": "omar.johnson456@example.com",
    "parent_phone": "(224) 555-1024",
    "campus": "Houston",
    "weeks": 1,
    "utm_source": "summer_site",
    "utm_medium": "referral",
    "utm_campaign": "summer_camp_2026",
    "created_at": "2026-07-16T00:00:00.000Z",
    "match_key": "d1bad5350132f267ae9a630a9fd1b61ee9779ab634a99a4f88dbfa7ed91f48ef"
  },
  {
    "_standIn": true,
    "_source": "registration_form",
    "form_id": "rf_3693232",
    "child_name": "Maya Jr",
    "parent_email": "maya.schwartz524@example.com",
    "parent_phone": "(301) 555-9045",
    "campus": "Austin",
    "weeks": 2,
    "utm_source": "summer_site",
    "utm_medium": "referral",
    "utm_campaign": "summer_camp_2026",
    "created_at": "2026-06-21T00:00:00.000Z",
    "match_key": "0d5d69f42fe4dc19075e0708442bfaae05fd8da22860fa4a5ad78c17293f910f"
  },
  {
    "_standIn": true,
    "_source": "registration_form",
    "form_id": "rf_0695106",
    "child_name": "Layla Jr",
    "parent_email": "layla.schwartz799@example.com",
    "parent_phone": "(828) 555-0962",
    "campus": "Georgetown",
    "weeks": 2,
    "utm_source": "summer_site",
    "utm_medium": "referral",
    "utm_campaign": "summer_camp_2026",
    "created_at": "2026-06-08T00:00:00.000Z",
    "match_key": "395cf3c4294c27d09896488d14ef0cc010ac2b07bb8a42f2a08d417c0cbc5942"
  },
  {
    "_standIn": true,
    "_source": "registration_form",
    "form_id": "rf_8988596",
    "child_name": "Aisha Jr",
    "parent_email": "aisha.adams1067@example.com",
    "parent_phone": "(289) 555-4621",
    "campus": "Austin",
    "weeks": 2,
    "utm_source": "summer_site",
    "utm_medium": "referral",
    "utm_campaign": "summer_camp_2026",
    "created_at": "2026-07-23T00:00:00.000Z",
    "match_key": "6123ee4dd93499603079f87480ad6704ced642ed32394afae1debaf0871c6186"
  },
  {
    "_standIn": true,
    "_source": "registration_form",
    "form_id": "rf_7734972",
    "child_name": "Sara Jr",
    "parent_email": "sara.martinez896@example.com",
    "parent_phone": "(294) 555-3296",
    "campus": "Austin",
    "weeks": 2,
    "utm_source": "summer_site",
    "utm_medium": "referral",
    "utm_campaign": "summer_camp_2026",
    "created_at": "2026-06-29T00:00:00.000Z",
    "match_key": "048a34f68b311a8f17374bedaf86deaf99606a1604adc3e9be302529d18a5168"
  },
  {
    "_standIn": true,
    "_source": "registration_form",
    "form_id": "rf_0508962",
    "child_name": "Nina Jr",
    "parent_email": "nina.nguyen1060@example.com",
    "parent_phone": "(309) 555-1368",
    "campus": "Houston",
    "weeks": 1,
    "utm_source": "summer_site",
    "utm_medium": "referral",
    "utm_campaign": "summer_camp_2026",
    "created_at": "2026-06-10T00:00:00.000Z",
    "match_key": "6fbfe4fe1b99137067bf0e4dc5437e58799e459967e52f5215a370eed55d97e3"
  },
  {
    "_standIn": true,
    "_source": "registration_form",
    "form_id": "rf_8186463",
    "child_name": "Noah Jr",
    "parent_email": "noah.hernandez303@example.com",
    "parent_phone": "(560) 555-8915",
    "campus": "Austin",
    "weeks": 2,
    "utm_source": "summer_site",
    "utm_medium": "referral",
    "utm_campaign": "summer_camp_2026",
    "created_at": "2026-08-13T00:00:00.000Z",
    "match_key": "6bf086364ad16842331fa4182280010bb11786eece3f50524ed7508706728bf7"
  }
]
